pykeboola/__init__.py
pykeboola/client.py
pykeboola/jobs.py
pykeboola/tables.py
pykeboola-0.0.12.dist-info/LICENSE
pykeboola-0.0.12.dist-info/METADATA
pykeboola-0.0.12.dist-info/WHEEL
pykeboola-0.0.12.dist-info/top_level.txt
pykeboola-0.0.12.dist-info/RECORD
