Metadata-Version: 2.1
Name: pykeboola
Version: 0.0.12
Summary: Python package for interacting with Keboola
Author-email: Tomas Pachovsky <pachovst@gmail.com>
Project-URL: Homepage, https://github.com/Pachac/pykeboola
Project-URL: Issues, https://github.com/Pachac/pykeboola/issues
Classifier: Programming Language :: Python :: 3
Classifier: License :: OSI Approved :: MIT License
Classifier: Operating System :: OS Independent
Requires-Python: >=3.8
License-File: LICENSE
Requires-Dist: requests
